{
  "users": [
    {
      "username": "Puss in Boots",
      "mark-list": [
        10
      ],
      "post-list": []
    },
    {
      "username": "a",
      "mark-list": [],
      "post-list": [
        1,
        2,
        3,
        4,
        5,
        6,
        7,
        8,
        9,
        10
      ]
    },
    {
      "username": "z",
      "mark-list": [
        9
      ],
      "post-list": [
        11,
        12,
        13,
        14
      ]
    },
    {
      "username": "b",
      "mark-list": [],
      "post-list": []
    }
  ],
  "rooms": [
    {
      "id": 1,
      "title": "Forest cabin",
      "price": 1500,
      "number": 2,
      "area": 67,
      "floor": 1,
      "city": "75001",
      "contact": "0789123456",
      "address": "Pl. Vendôme",
      "location": {
        "lat": 48.8674692,
        "lng": 2.3296313
      },
      "url": [
        "https://rooom-image.s3.eu-west-3.amazonaws.com/1698519900747.webp",
        "https://rooom-image.s3.eu-west-3.amazonaws.com/1698519901220.webp"
      ]
    },
    {
      "id": 2,
      "title": "Two bedrooms with patio",
      "price": 1000,
      "number": 2,
      "area": 56,
      "floor": 6,
      "city": "75002",
      "contact": "0789123456",
      "address": "Bonne-Nouvelle",
      "location": {
        "lat": 48.8674501,
        "lng": 2.3496033
      },
      "url": [
        "https://rooom-image.s3.eu-west-3.amazonaws.com/1698519985447.webp",
        "https://rooom-image.s3.eu-west-3.amazonaws.com/1698519985841.webp"
      ]
    },
    {
      "id": 3,
      "title": "Third bedroom in Sunflower Garden",
      "price": 1500,
      "number": 2,
      "area": 56,
      "floor": 6,
      "city": "51000",
      "contact": "0789123456",
      "address": "20 Rue Pasteur",
      "location": {
        "lat": 48.9555154,
        "lng": 4.3664998
      },
      "url": [
        "https://rooom-image.s3.eu-west-3.amazonaws.com/1698520032707.webp",
        "https://rooom-image.s3.eu-west-3.amazonaws.com/1698520033100.webp"
      ]
    },
    {
      "id": 4,
      "title": "Châlons-en-Champagne",
      "price": 1500,
      "number": 2,
      "area": 56,
      "floor": 6,
      "city": "51000",
      "contact": "0789123456",
      "address": "1 Rue du Cirque",
      "location": {
        "lat": 48.9521144,
        "lng": 4.3594066
      },
      "url": []
    },
    {
      "id": 5,
      "title": "Perfect game cat's house",
      "price": 1000,
      "number": 2,
      "area": 56,
      "floor": 6,
      "city": "10000",
      "contact": "0789123456",
      "address": "35 Rue de Preize",
      "location": {
        "lat": 48.3019678,
        "lng": 4.0732172
      },
      "url": [
        "https://rooom-image.s3.eu-west-3.amazonaws.com/1698520186400.webp",
        "https://rooom-image.s3.eu-west-3.amazonaws.com/1698520186802.webp"
      ]
    },
    {
      "id": 6,
      "title": "3 bedrooms with no kitchen",
      "price": 1500,
      "number": 2,
      "area": 56,
      "floor": 6,
      "city": "10000",
      "contact": "0789123456",
      "address": "19 Bd Danton",
      "location": {
        "lat": 48.3039183,
        "lng": 4.075934
      },
      "url": [
        "https://rooom-image.s3.eu-west-3.amazonaws.com/1698520245972.webp",
        "https://rooom-image.s3.eu-west-3.amazonaws.com/1698520246392.webp"
      ]
    },
    {
      "id": 7,
      "title": "The ideal home for meditating cats",
      "price": 1000,
      "number": 2,
      "area": 56,
      "floor": 6,
      "city": "10000",
      "contact": "0789123456",
      "address": "Pharmacie Chomedey",
      "location": {
        "lat": 48.303841,
        "lng": 4.073263799999999
      },
      "url": [
        "https://rooom-image.s3.eu-west-3.amazonaws.com/1698520273737.webp"
      ]
    },
    {
      "id": 8,
      "title": "A large one-bedroom apartment with a shared kitchen",
      "price": 120,
      "number": 1,
      "area": 56,
      "floor": 6,
      "address": "1 rue de la trinitie",
      "city": "10000",
      "location": {
        "lat": 48.2951634,
        "lng": 4.0727335
      },
      "contact": "Merci de contacter l'écureuil sur le deuxième arbre de gauche à droite en bas du bâtiment, il est toujours là.",
      "url": [
        "https://rooom-image.s3.eu-west-3.amazonaws.com/1698521392196.webp",
        "https://rooom-image.s3.eu-west-3.amazonaws.com/1698521392550.webp"
      ]
    },
    {
      "city": "51000",
      "price": 33,
      "title": "Great accommodation with huge kitchen and cats service included",
      "number": 3,
      "area": 333,
      "floor": 3,
      "address": "1 Rue Thomas Martin",
      "location": {
        "lat": 48.9545365,
        "lng": 4.362650599999999
      },
      "contact": " Contact Cat directly",
      "url": [
        "https://rooom-image.s3.eu-west-3.amazonaws.com/1698521415561.webp",
        "https://rooom-image.s3.eu-west-3.amazonaws.com/1698521415998.webp"
      ],
      "id": 9
    },
    {
      "city": "51000",
      "price": 44,
      "title": " Space style living room, rent with caution if you are not skilled in high technology",
      "number": 44,
      "area": 44,
      "floor": 4,
      "address": "1C Rue Robert Espagne",
      "location": {
        "lat": 48.948633,
        "lng": 4.3417618
      },
      "contact": "The password of the electronic lock is the answer to this puzzle ******",
      "url": [
        "https://rooom-image.s3.eu-west-3.amazonaws.com/1698521435146.webp",
        "https://rooom-image.s3.eu-west-3.amazonaws.com/1698521435528.webp"
      ],
      "id": 10
    },
    {
      "city": "10000",
      "price": 88,
      "title": "Bathtub water pressure is unstable",
      "number": 88,
      "area": 88,
      "floor": 8,
      "address": "ibis troyes center",
      "location": {
        "lat": 48.2929548,
        "lng": 4.0805966
      },
      "contact": "12345678",
      "url": [
        "https://rooom-image.s3.eu-west-3.amazonaws.com/1698521488396.webp",
        "https://rooom-image.s3.eu-west-3.amazonaws.com/1698521489090.webp",
        "https://rooom-image.s3.eu-west-3.amazonaws.com/1698521489382.webp",
        "https://rooom-image.s3.eu-west-3.amazonaws.com/1698521489697.webp"
      ],
      "id": 11
    },
    {
      "city": "93290",
      "price": 99,
      "title": "Simple wooden single-family building, no bathroom, you can borrow a cat",
      "number": 9,
      "area": 99,
      "floor": 1,
      "address": "6 Rue de Madrid",
      "location": {
        "lat": 49.0107436,
        "lng": 2.5687704
      },
      "contact": "999",
      "url": [
        "https://rooom-image.s3.eu-west-3.amazonaws.com/1698521564431.webp"
      ],
      "id": 12
    },
    {
      "city": "10000",
      "price": 11,
      "title": "Big enough for two cats which is located in the city center with cat grass nearby",
      "number": 1,
      "area": 111,
      "floor": 1,
      "address": "54 Bd Gambetta, Troyes",
      "location": {
        "lat": 48.2983055,
        "lng": 4.0681992
      },
      "contact": "33333",
      "url": [
        "https://rooom-image.s3.eu-west-3.amazonaws.com/1698956099682.webp"
      ],
      "id": 13
    },
    {
      "city": "10000",
      "price": 22,
      "address": "41 Rue Jules Lebocey",
      "location": {
        "lat": 48.2983047,
        "lng": 4.0713484
      },
      "contact": "33333",
      "title": " Fully furnished one bedroom appartment",
      "number": 1,
      "area": 2,
      "floor": 2,
      "url": [
        "https://rooom-image.s3.eu-west-3.amazonaws.com/1698957620525.webp"
      ],
      "id": 14
    }
  ]
}